setup.py
buy_sell_ex_forex_next3/__init__.py
buy_sell_ex_forex_next3/buy_sell_ex_forex_next3.py
buy_sell_ex_forex_next3.egg-info/PKG-INFO
buy_sell_ex_forex_next3.egg-info/SOURCES.txt
buy_sell_ex_forex_next3.egg-info/dependency_links.txt
buy_sell_ex_forex_next3.egg-info/not-zip-safe
buy_sell_ex_forex_next3.egg-info/top_level.txt