Metadata-Version: 1.0
Name: buy-sell-ex-forex-next3
Version: 1.20
Summary: buy_sell_ex_forex_next3
Home-page: UNKNOWN
Author: omid
Author-email: UNKNOWN
License: UNKNOWN
Platform: UNKNOWN
